{"_id":{"$oid":"68ac43a2e68d76edfe9666ad"},"ticker":"AAP","company":"Advance Auto Parts","userId":{"$oid":"68ac38cb3c01f9c42c27f00b"},"__v":0,"averageCost":0,"position":false,"watchList":true}
{"_id":{"$oid":"68ac5ca3e68d76edfe9666b5"},"ticker":"ALLE","company":"Allegion","userId":{"$oid":"68ac38cb3c01f9c42c27f00b"},"__v":0,"averageCost":0,"position":false,"watchList":true,"positionSize":24.49}
{"_id":{"$oid":"68ac5e0b00eb2cc9fe421b1c"},"ticker":"APLD","company":"Applied Digital","userId":{"$oid":"68ac38cb3c01f9c42c27f00b"},"__v":0,"averageCost":0,"position":false,"watchList":true,"positionSize":3.37}
{"_id":{"$oid":"68ae01a7bb106abec71e79a9"},"ticker":"AVGO","company":"Broadcom","__v":0,"averageCost":0,"position":false,"watchList":true,"userId":{"$oid":"68ac38cb3c01f9c42c27f00b"}}
{"_id":{"$oid":"68ae027bbb106abec71e79b2"},"ticker":"B","company":"Barrick Mining","__v":0,"averageCost":29.31,"position":true,"watchList":false,"positionSize":2.65,"userId":{"$oid":"68ac38cb3c01f9c42c27f00b"}}
{"_id":{"$oid":"68ae148b67ae4aa4b6d20cbb"},"ticker":"BTC-USD","company":"Bitcoin","averageCost":0,"__v":0,"position":false,"watchList":true,"userId":{"$oid":"68ac38cb3c01f9c42c27f00b"}}
{"_id":{"$oid":"68ae14bf67ae4aa4b6d20cbe"},"ticker":"NET","company":"Cloudflare","averageCost":0,"__v":0,"position":false,"watchList":true,"positionSize":29.27,"userId":{"$oid":"68ac38cb3c01f9c42c27f00b"}}
{"_id":{"$oid":"68af13d48a1e2cea2277fee1"},"ticker":"BAC","company":"Bank of America","averageCost":51.14,"__v":0,"position":true,"watchList":false,"positionSize":19.16,"userId":{"$oid":"68ac38cb3c01f9c42c27f00b"}}
{"_id":{"$oid":"68af1a9f335834980c36c09a"},"ticker":"LYFT","company":"Lyft","averageCost":0,"__v":0,"position":false,"watchList":true,"positionSize":2.27,"userId":{"$oid":"68ac38cb3c01f9c42c27f00b"}}
{"_id":{"$oid":"68af1b64335834980c36c0a0"},"ticker":"MZTI","company":"The Marzeti Company","averageCost":null,"__v":0,"position":false,"watchList":true,"userId":{"$oid":"68ac38cb3c01f9c42c27f00b"}}
{"_id":{"$oid":"68af1b97335834980c36c0a3"},"ticker":"OSCR","company":"Oscar Health","averageCost":null,"__v":0,"position":false,"watchList":true,"userId":{"$oid":"68ac38cb3c01f9c42c27f00b"}}
{"_id":{"$oid":"68af42e6e206b6fdc439233d"},"ticker":"SOFI","company":"SoFi Technologies","averageCost":0,"__v":0,"position":false,"watchList":true,"positionSize":21.37,"userId":{"$oid":"68ac38cb3c01f9c42c27f00b"}}
{"_id":{"$oid":"68af43d7e206b6fdc4392346"},"ticker":"DIA","company":"SPDR Dow Jones Industrial Average ETF","averageCost":462.91,"__v":0,"position":true,"watchList":false,"positionSize":40,"userId":{"$oid":"68ac38cb3c01f9c42c27f00b"}}
{"_id":{"$oid":"68af45c7e206b6fdc439234c"},"ticker":"SPY","company":"SPDR S&P 500 ETF","averageCost":661.84,"__v":0,"position":true,"watchList":false,"positionSize":40,"userId":{"$oid":"68ac38cb3c01f9c42c27f00b"}}
{"_id":{"$oid":"68af462fe206b6fdc4392355"},"ticker":"CVX","company":"Chevron","averageCost":160.09,"__v":0,"position":true,"watchList":false,"positionSize":35,"userId":{"$oid":"68ac38cb3c01f9c42c27f00b"}}
{"_id":{"$oid":"68af4665e206b6fdc439235b"},"ticker":"RKT","company":"Rocket Companies","averageCost":0,"__v":0,"position":false,"watchList":true,"userId":{"$oid":"68ac38cb3c01f9c42c27f00b"}}
{"_id":{"$oid":"68af4687e206b6fdc4392367"},"ticker":"OPEN","company":"Opendoor Technologies","averageCost":0,"__v":0,"position":false,"watchList":true,"userId":{"$oid":"68ac38cb3c01f9c42c27f00b"}}
{"_id":{"$oid":"68af468de206b6fdc439236a"},"ticker":"OKLO","company":"Oklo","averageCost":0,"__v":0,"position":false,"watchList":true,"positionSize":1.59,"userId":{"$oid":"68ac38cb3c01f9c42c27f00b"}}
{"_id":{"$oid":"68af46f1e206b6fdc4392371"},"ticker":"W","company":"Wayfair","averageCost":0,"__v":0,"position":false,"watchList":true,"userId":{"$oid":"68ac38cb3c01f9c42c27f00b"}}
{"_id":{"$oid":"68af46f6e206b6fdc4392377"},"ticker":"JNJ","company":"Johnson & Johnson","averageCost":0,"__v":0,"position":false,"watchList":true,"userId":{"$oid":"68ac38cb3c01f9c42c27f00b"}}
{"_id":{"$oid":"68af46ffe206b6fdc4392383"},"ticker":"T","company":"AT&T","averageCost":0,"__v":0,"position":false,"watchList":true,"userId":{"$oid":"68ac38cb3c01f9c42c27f00b"}}
{"_id":{"$oid":"68af4717e206b6fdc4392392"},"ticker":"PAAS","company":"Pan American Silver","averageCost":38.28,"__v":0,"position":true,"watchList":false,"positionSize":9,"userId":{"$oid":"68ac38cb3c01f9c42c27f00b"}}
{"_id":{"$oid":"68af4731e206b6fdc43923b0"},"ticker":"QQQ","company":"Invesco QQQ","averageCost":595.98,"__v":0,"position":true,"watchList":false,"positionSize":40,"userId":{"$oid":"68ac38cb3c01f9c42c27f00b"}}
{"_id":{"$oid":"68af473be206b6fdc43923bf"},"ticker":"RDDT","company":"Reddit","averageCost":0,"__v":0,"position":false,"watchList":true,"userId":{"$oid":"68ac38cb3c01f9c42c27f00b"}}
{"_id":{"$oid":"68af4745e206b6fdc43923c8"},"ticker":"GS","company":"Goldman Sachs","averageCost":802.47,"__v":0,"position":true,"watchList":false,"positionSize":38,"userId":{"$oid":"68ac38cb3c01f9c42c27f00b"}}
{"_id":{"$oid":"68af4746e206b6fdc43923cb"},"ticker":"GOOG","company":"Alphabet Class C","averageCost":0,"__v":0,"position":false,"watchList":true,"positionSize":21.33,"userId":{"$oid":"68ac38cb3c01f9c42c27f00b"}}
{"_id":{"$oid":"68af4748e206b6fdc43923ce"},"ticker":"GOOGL","company":"Alphabet Class A","averageCost":0,"__v":0,"position":false,"watchList":true,"positionSize":21.28,"userId":{"$oid":"68ac38cb3c01f9c42c27f00b"}}
{"_id":{"$oid":"68af4755e206b6fdc43923d7"},"ticker":"GE","company":"General Electric","averageCost":0,"__v":0,"position":false,"watchList":true,"positionSize":14.66,"userId":{"$oid":"68ac38cb3c01f9c42c27f00b"}}
{"_id":{"$oid":"68af4757e206b6fdc43923da"},"ticker":"MS","company":"Morgan Stanley","averageCost":161.1,"__v":0,"position":true,"watchList":false,"positionSize":28,"userId":{"$oid":"68ac38cb3c01f9c42c27f00b"}}
{"_id":{"$oid":"68af4761e206b6fdc43923e0"},"ticker":"QCOM","company":"Qualcomm","averageCost":161.63,"__v":0,"position":true,"watchList":false,"positionSize":10.13,"userId":{"$oid":"68ac38cb3c01f9c42c27f00b"}}
{"_id":{"$oid":"68af4766e206b6fdc43923e6"},"ticker":"PZZA","company":"Papa John's","averageCost":0,"__v":0,"position":false,"watchList":true,"userId":{"$oid":"68ac38cb3c01f9c42c27f00b"}}
{"_id":{"$oid":"68af4769e206b6fdc43923e9"},"ticker":"C","company":"Citigroup","averageCost":99.71,"__v":0,"position":true,"watchList":false,"positionSize":13.16,"userId":{"$oid":"68ac38cb3c01f9c42c27f00b"}}
{"_id":{"$oid":"68af4772e206b6fdc43923ef"},"ticker":"CHAT","company":"Roundhill Generative AI & Technology ETF","averageCost":0,"__v":0,"position":false,"watchList":true,"positionSize":12.06,"userId":{"$oid":"68ac38cb3c01f9c42c27f00b"}}
{"_id":{"$oid":"68af4775e206b6fdc43923f2"},"ticker":"GROY","company":"Gold Royalty","averageCost":3.86,"__v":0,"position":true,"watchList":false,"positionSize":10,"userId":{"$oid":"68ac38cb3c01f9c42c27f00b"}}
{"_id":{"$oid":"68af4787e206b6fdc43923fb"},"ticker":"GM","company":"GM","averageCost":61.17,"__v":0,"position":true,"watchList":false,"positionSize":12,"userId":{"$oid":"68ac38cb3c01f9c42c27f00b"}}
{"_id":{"$oid":"68af4790e206b6fdc4392401"},"ticker":"JPM","company":"JPMorgan Chase","averageCost":312.12,"__v":0,"position":true,"watchList":false,"positionSize":31.69,"userId":{"$oid":"68ac38cb3c01f9c42c27f00b"}}
{"_id":{"$oid":"68af4793e206b6fdc4392404"},"ticker":"WULF","company":"TeraWulf","averageCost":0,"__v":0,"position":false,"watchList":true,"positionSize":10.78,"userId":{"$oid":"68ac38cb3c01f9c42c27f00b"}}
{"_id":{"$oid":"68af479ee206b6fdc439240d"},"ticker":"ORLY","company":"O'Reilly Auto Parts","averageCost":105.94,"__v":0,"position":true,"watchList":false,"positionSize":28,"userId":{"$oid":"68ac38cb3c01f9c42c27f00b"}}
{"_id":{"$oid":"68af47bfe206b6fdc439241f"},"ticker":"CVS","company":"CVS","averageCost":74.41,"__v":0,"position":true,"watchList":false,"positionSize":15.83,"userId":{"$oid":"68ac38cb3c01f9c42c27f00b"}}
{"_id":{"$oid":"68af47d7e206b6fdc4392428"},"ticker":"UNH","company":"UnitedHealth","averageCost":344.95,"__v":0,"position":true,"watchList":false,"positionSize":37,"userId":{"$oid":"68ac38cb3c01f9c42c27f00b"}}
{"_id":{"$oid":"68af5af5e464b97505877597"},"ticker":"GLD","company":"SPDR Gold Trust","averageCost":338.71,"__v":0,"position":true,"watchList":false,"positionSize":14.02,"userId":{"$oid":"68ac38cb3c01f9c42c27f00b"}}
{"_id":{"$oid":"68b09ffed1b4093d18aa4a15"},"ticker":"AZO","company":"AutoZone","averageCost":4208.75,"__v":0,"position":true,"watchList":false,"positionSize":40,"userId":{"$oid":"68ac38cb3c01f9c42c27f00b"}}
{"_id":{"$oid":"68b57766da58b32f7cf5f357"},"ticker":"PANW","company":"Palo Alto Networks","averageCost":0,"__v":0,"position":false,"watchList":true,"positionSize":14.35,"userId":{"$oid":"68ac38cb3c01f9c42c27f00b"}}
{"_id":{"$oid":"68b7185cb58dfb5ea8b8686e"},"ticker":"BBW","company":"Build A Bear","averageCost":0,"__v":0,"position":false,"watchList":true,"userId":{"$oid":"68ac38cb3c01f9c42c27f00b"}}
{"_id":{"$oid":"68b73c34b58dfb5ea8b868b4"},"ticker":"RBLX","company":"Roblox","averageCost":0,"__v":0,"position":false,"watchList":true,"positionSize":23.07,"userId":{"$oid":"68ac38cb3c01f9c42c27f00b"}}
{"_id":{"$oid":"68b7666fb58dfb5ea8b86914"},"ticker":"HD","company":"Home Depot","averageCost":0,"__v":0,"position":false,"watchList":true,"userId":{"$oid":"68ac38cb3c01f9c42c27f00b"}}
{"_id":{"$oid":"68b87a9eb58dfb5ea8b86930"},"ticker":"AEO","company":"American Eagle","averageCost":0,"__v":0,"position":false,"watchList":true,"userId":{"$oid":"68ac38cb3c01f9c42c27f00b"}}
{"_id":{"$oid":"68b87b1cb58dfb5ea8b8693f"},"ticker":"LOW","company":"Lowe's","averageCost":0,"__v":0,"position":false,"watchList":true,"userId":{"$oid":"68ac38cb3c01f9c42c27f00b"}}
{"_id":{"$oid":"68b87b37b58dfb5ea8b86942"},"ticker":"M","company":"Macy's","averageCost":17.97,"__v":0,"position":true,"watchList":false,"positionSize":13,"userId":{"$oid":"68ac38cb3c01f9c42c27f00b"}}
{"_id":{"$oid":"68b87b4cb58dfb5ea8b86945"},"ticker":"MDB","company":"MongoDB","averageCost":0,"__v":0,"position":false,"watchList":true,"userId":{"$oid":"68ac38cb3c01f9c42c27f00b"}}
{"_id":{"$oid":"68b87b61b58dfb5ea8b86948"},"ticker":"PBA","company":"Pembina","averageCost":39.11,"__v":0,"position":true,"watchList":false,"positionSize":19.36,"userId":{"$oid":"68ac38cb3c01f9c42c27f00b"}}
{"_id":{"$oid":"68b87c0db58dfb5ea8b86958"},"ticker":"TSLA","company":"Tesla","averageCost":414.96,"__v":0,"position":true,"watchList":false,"positionSize":4.4,"userId":{"$oid":"68ac38cb3c01f9c42c27f00b"}}
{"_id":{"$oid":"68b88e1fb58dfb5ea8b869eb"},"ticker":"WMT","company":"Walmart","averageCost":0,"__v":0,"position":false,"watchList":true,"userId":{"$oid":"68ac38cb3c01f9c42c27f00b"}}
{"_id":{"$oid":"68b9c52cd9f05b846d72de7f"},"ticker":"WIX","company":"Wix.com","averageCost":0,"__v":0,"position":false,"watchList":true,"positionSize":8.69,"userId":{"$oid":"68ac38cb3c01f9c42c27f00b"}}
{"_id":{"$oid":"68b9cbfdd9f05b846d72de9f"},"ticker":"DOCU","company":"Docusign","averageCost":0,"__v":0,"position":false,"watchList":true,"positionSize":11.52,"userId":{"$oid":"68ac38cb3c01f9c42c27f00b"}}
{"_id":{"$oid":"68b9e24ed9f05b846d72df4c"},"ticker":"META","company":"Meta Platforms","averageCost":0,"__v":0,"position":false,"watchList":true,"userId":{"$oid":"68ac38cb3c01f9c42c27f00b"}}
{"_id":{"$oid":"68b9e696d9f05b846d72df7c"},"ticker":"CAT","company":"Caterpillar","averageCost":440.21,"__v":0,"position":true,"watchList":false,"positionSize":11.57,"userId":{"$oid":"68ac38cb3c01f9c42c27f00b"}}
{"_id":{"$oid":"68bb25ea3beccfac0aea5bb9"},"ticker":"PBPB","company":"Potbelly","averageCost":12.6,"__v":0,"position":true,"watchList":false,"positionSize":3.35,"userId":{"$oid":"68ac38cb3c01f9c42c27f00b"}}
{"_id":{"$oid":"68bb3293a2e1691317a5b072"},"ticker":"TSM","company":"Taiwan Semiconductor Manufacturing","averageCost":262.29,"__v":0,"position":true,"watchList":false,"positionSize":6.43,"userId":{"$oid":"68ac38cb3c01f9c42c27f00b"}}
{"_id":{"$oid":"68bb351da2e1691317a5b088"},"ticker":"DLTH","company":"Duluth Holdings","averageCost":0,"__v":0,"position":false,"watchList":true,"userId":{"$oid":"68ac38cb3c01f9c42c27f00b"}}
{"_id":{"$oid":"68bb38f2a2e1691317a5b0ab"},"ticker":"BLNE","company":"Beeline Holdings","averageCost":2.23,"__v":0,"position":true,"watchList":false,"positionSize":1.82,"userId":{"$oid":"68ac38cb3c01f9c42c27f00b"}}
{"_id":{"$oid":"68bb39b5a2e1691317a5b0b4"},"ticker":"CPRT","company":"Copart","averageCost":null,"__v":0,"position":false,"watchList":true,"userId":{"$oid":"68ac38cb3c01f9c42c27f00b"}}
{"_id":{"$oid":"68be2139c826a7d6d3dc53c2"},"ticker":"HOOD","company":"Robinhood","averageCost":0,"__v":0,"position":false,"watchList":true,"positionSize":10.31,"userId":{"$oid":"68ac38cb3c01f9c42c27f00b"}}
{"_id":{"$oid":"68be2154c826a7d6d3dc53c5"},"ticker":"APP","company":"AppLovin","averageCost":589.42,"__v":0,"position":true,"watchList":false,"positionSize":5.74,"userId":{"$oid":"68ac38cb3c01f9c42c27f00b"}}
{"_id":{"$oid":"68be2281c826a7d6d3dc53c8"},"ticker":"EME","company":"Emcor","averageCost":640.79,"__v":0,"position":true,"watchList":false,"positionSize":28,"userId":{"$oid":"68ac38cb3c01f9c42c27f00b"}}
{"_id":{"$oid":"68bedfafb55cd4235caecb73"},"ticker":"SATS","company":"EchoStar","averageCost":73.84,"__v":0,"position":true,"watchList":false,"positionSize":19,"userId":{"$oid":"68ac38cb3c01f9c42c27f00b"}}
{"_id":{"$oid":"68bf1999c6413d2c296111c7"},"ticker":"DASH","company":"DoorDash","averageCost":0,"__v":0,"position":false,"watchList":true,"positionSize":21.02,"userId":{"$oid":"68ac38cb3c01f9c42c27f00b"}}
{"_id":{"$oid":"68c18ee2f95d7d5385fe5f5b"},"ticker":"IREN","company":"IREN Limited","averageCost":35.81,"__v":0,"position":true,"watchList":false,"positionSize":2.92,"userId":{"$oid":"68ac38cb3c01f9c42c27f00b"}}
{"_id":{"$oid":"68c1d284f95d7d5385fe5fc9"},"ticker":"DUK","company":"Duke Energy","averageCost":122.32,"__v":0,"position":true,"watchList":false,"positionSize":40,"userId":{"$oid":"68ac38cb3c01f9c42c27f00b"}}
{"_id":{"$oid":"68c30771f95d7d5385fe6041"},"ticker":"F","company":"Ford Motor","averageCost":12.03,"__v":0,"position":true,"watchList":false,"positionSize":14,"userId":{"$oid":"68ac38cb3c01f9c42c27f00b"}}
{"_id":{"$oid":"68c3117ef95d7d5385fe6087"},"ticker":"TEM","company":"Tempus AI","averageCost":0,"__v":0,"position":false,"watchList":true,"positionSize":8.04,"userId":{"$oid":"68ac38cb3c01f9c42c27f00b"}}
{"_id":{"$oid":"68c31264f95d7d5385fe6096"},"ticker":"UBER","company":"Uber","averageCost":98.31,"__v":0,"position":true,"watchList":false,"positionSize":39.56,"userId":{"$oid":"68ac38cb3c01f9c42c27f00b"}}
{"_id":{"$oid":"68c313a0f95d7d5385fe60aa"},"ticker":"WFC","company":"Wells Fargo","averageCost":82.7,"__v":0,"position":true,"watchList":false,"positionSize":25.11,"userId":{"$oid":"68ac38cb3c01f9c42c27f00b"}}
{"_id":{"$oid":"68c314d7f95d7d5385fe60b3"},"ticker":"XOM","company":"Exxon Mobil","averageCost":117.74,"__v":0,"position":true,"watchList":false,"positionSize":13,"userId":{"$oid":"68ac38cb3c01f9c42c27f00b"}}
{"_id":{"$oid":"68c31c5bf95d7d5385fe60f0"},"ticker":"DAVE","company":"Dave","averageCost":0,"__v":0,"position":false,"watchList":true,"positionSize":5.04,"userId":{"$oid":"68ac38cb3c01f9c42c27f00b"}}
{"_id":{"$oid":"68c31cd5f95d7d5385fe60f9"},"ticker":"DDOG","company":"Datadog","averageCost":138.53,"__v":0,"position":true,"watchList":false,"positionSize":38,"userId":{"$oid":"68ac38cb3c01f9c42c27f00b"}}
{"_id":{"$oid":"68c31d67f95d7d5385fe6102"},"ticker":"HIMS","company":"Hims","averageCost":57.83,"__v":0,"position":true,"watchList":false,"positionSize":8,"userId":{"$oid":"68ac38cb3c01f9c42c27f00b"}}
{"_id":{"$oid":"68c31d96f95d7d5385fe6107"},"ticker":"HWM","company":"Howmet Aerospace","averageCost":193.92,"__v":0,"position":true,"watchList":false,"positionSize":22,"userId":{"$oid":"68ac38cb3c01f9c42c27f00b"}}
{"_id":{"$oid":"68c31dc9f95d7d5385fe610a"},"ticker":"IONQ","company":"Ionq","averageCost":0,"__v":0,"position":false,"watchList":true,"positionSize":2.54,"userId":{"$oid":"68ac38cb3c01f9c42c27f00b"}}
{"_id":{"$oid":"68c31dd9f95d7d5385fe610d"},"ticker":"NVDA","company":"Nvidia","averageCost":177.58,"__v":0,"position":true,"watchList":false,"positionSize":37,"userId":{"$oid":"68ac38cb3c01f9c42c27f00b"}}
{"_id":{"$oid":"68c31deaf95d7d5385fe6110"},"ticker":"ORCL","company":"Oracle","averageCost":0,"__v":0,"position":false,"watchList":true,"positionSize":5.81,"userId":{"$oid":"68ac38cb3c01f9c42c27f00b"}}
{"_id":{"$oid":"68c31dfff95d7d5385fe6113"},"ticker":"PLTR","company":"Palantir Technologies","averageCost":170.49,"__v":0,"position":true,"watchList":false,"positionSize":10.16,"userId":{"$oid":"68ac38cb3c01f9c42c27f00b"}}
{"_id":{"$oid":"68c31e17f95d7d5385fe6116"},"ticker":"PM","company":"Phillip Morris","averageCost":163.83,"__v":0,"position":true,"watchList":false,"positionSize":37,"userId":{"$oid":"68ac38cb3c01f9c42c27f00b"}}
{"_id":{"$oid":"68c31e2ef95d7d5385fe6119"},"ticker":"WBD","company":"Warner Bros. Discovery","averageCost":18.28,"__v":0,"position":true,"watchList":false,"positionSize":4.34,"userId":{"$oid":"68ac38cb3c01f9c42c27f00b"}}
{"_id":{"$oid":"68c31e46f95d7d5385fe611c"},"ticker":"YUM","company":"Yum!","averageCost":152.21,"__v":0,"position":true,"watchList":false,"positionSize":17,"userId":{"$oid":"68ac38cb3c01f9c42c27f00b"}}
{"_id":{"$oid":"68c321cff95d7d5385fe6140"},"ticker":"PLD","company":"Prologis","averageCost":114.3,"__v":0,"position":true,"watchList":false,"positionSize":37,"userId":{"$oid":"68ac38cb3c01f9c42c27f00b"}}
{"_id":{"$oid":"68c32436f95d7d5385fe6152"},"ticker":"ISPC","company":"iSpecimen","averageCost":0,"__v":0,"position":false,"watchList":true,"userId":{"$oid":"68ac38cb3c01f9c42c27f00b"}}
{"_id":{"$oid":"68c3275af95d7d5385fe616a"},"ticker":"CAG","company":"Conagra","averageCost":null,"__v":0,"position":false,"watchList":true,"userId":{"$oid":"68ac38cb3c01f9c42c27f00b"}}
{"_id":{"$oid":"68c3287df95d7d5385fe617a"},"ticker":"DIN","company":"Dine Brands","averageCost":24.27,"__v":0,"position":true,"watchList":false,"positionSize":32,"userId":{"$oid":"68ac38cb3c01f9c42c27f00b"}}
{"_id":{"$oid":"68c32946f95d7d5385fe6186"},"ticker":"ET","company":"Energy Transfer","averageCost":17.49,"__v":0,"position":true,"watchList":false,"positionSize":38,"userId":{"$oid":"68ac38cb3c01f9c42c27f00b"}}
{"_id":{"$oid":"68c329c2f95d7d5385fe618f"},"ticker":"GIS","company":"General Mills","averageCost":0,"__v":0,"position":false,"watchList":true,"positionSize":40.12,"userId":{"$oid":"68ac38cb3c01f9c42c27f00b"}}
{"_id":{"$oid":"68c32a48f95d7d5385fe6198"},"ticker":"GME","company":"GameStop","averageCost":0,"__v":0,"position":false,"watchList":true,"positionSize":20.14,"userId":{"$oid":"68ac38cb3c01f9c42c27f00b"}}
{"_id":{"$oid":"68c32c83f95d7d5385fe619e"},"ticker":"LLY","company":"Eli Lilly","averageCost":0,"__v":0,"position":false,"watchList":true,"userId":{"$oid":"68ac38cb3c01f9c42c27f00b"}}
{"_id":{"$oid":"68c3e8d0a3afe7c4de9db78e"},"ticker":"SMCI","company":"Super Micro Computer","averageCost":0,"__v":0,"position":false,"watchList":true,"positionSize":8.45,"userId":{"$oid":"68ac38cb3c01f9c42c27f00b"}}
{"_id":{"$oid":"68c3e92da3afe7c4de9db791"},"ticker":"QUBT","company":"Quantum Computing","averageCost":18.09,"__v":0,"position":true,"watchList":false,"positionSize":3.81,"userId":{"$oid":"68ac38cb3c01f9c42c27f00b"}}
{"_id":{"$oid":"68c3e961a3afe7c4de9db794"},"ticker":"QSR","company":"Restaurant Brands International","averageCost":63.53,"__v":0,"position":true,"watchList":false,"positionSize":40.4,"userId":{"$oid":"68ac38cb3c01f9c42c27f00b"}}
{"_id":{"$oid":"68c3e9dca3afe7c4de9db797"},"ticker":"NVTS","company":"Navitas Semiconductor","averageCost":0,"__v":0,"position":false,"watchList":true,"positionSize":6.17,"userId":{"$oid":"68ac38cb3c01f9c42c27f00b"}}
{"_id":{"$oid":"68c3ea2ba3afe7c4de9db79d"},"ticker":"MARA","company":"MARA Holdings","averageCost":0,"__v":0,"position":false,"watchList":true,"positionSize":6.76,"userId":{"$oid":"68ac38cb3c01f9c42c27f00b"}}
{"_id":{"$oid":"68c3ea56a3afe7c4de9db7a0"},"ticker":"IBM","company":"IBM","averageCost":260.99,"__v":0,"position":true,"watchList":false,"positionSize":15.31,"userId":{"$oid":"68ac38cb3c01f9c42c27f00b"}}
{"_id":{"$oid":"68c3ea70a3afe7c4de9db7a3"},"ticker":"HUBC","company":"Hub Cyber Security","averageCost":0,"__v":0,"position":false,"watchList":true,"userId":{"$oid":"68ac38cb3c01f9c42c27f00b"}}
{"_id":{"$oid":"68c3ea99a3afe7c4de9db7a6"},"ticker":"GT","company":"Goodyear","averageCost":0,"__v":0,"position":false,"watchList":true,"userId":{"$oid":"68ac38cb3c01f9c42c27f00b"}}
{"_id":{"$oid":"68c3eacaa3afe7c4de9db7a9"},"ticker":"FDX","company":"FedEx","averageCost":233.98,"__v":0,"position":true,"watchList":false,"positionSize":17,"userId":{"$oid":"68ac38cb3c01f9c42c27f00b"}}
{"_id":{"$oid":"68c3eb32a3afe7c4de9db7af"},"ticker":"DTE","company":"DTE","averageCost":136.08,"__v":0,"position":true,"watchList":false,"positionSize":40.02,"userId":{"$oid":"68ac38cb3c01f9c42c27f00b"}}
{"_id":{"$oid":"68c3eb4ea3afe7c4de9db7b2"},"ticker":"DELL","company":"Dell","averageCost":0,"__v":0,"position":false,"watchList":true,"positionSize":16.09,"userId":{"$oid":"68ac38cb3c01f9c42c27f00b"}}
{"_id":{"$oid":"68c3eb7ba3afe7c4de9db7b5"},"ticker":"CRWV","company":"CoreWeave","averageCost":0,"__v":0,"position":false,"watchList":true,"positionSize":6.76,"userId":{"$oid":"68ac38cb3c01f9c42c27f00b"}}
{"_id":{"$oid":"68c3eba2a3afe7c4de9db7b8"},"ticker":"CRWD","company":"CrowdStrike Holdings","averageCost":458.97,"__v":0,"position":true,"watchList":false,"positionSize":6.21,"userId":{"$oid":"68ac38cb3c01f9c42c27f00b"}}
{"_id":{"$oid":"68c3ebbfa3afe7c4de9db7bb"},"ticker":"CRCL","company":"Circle Internet Group","averageCost":0,"__v":0,"position":false,"watchList":true,"positionSize":6.41,"userId":{"$oid":"68ac38cb3c01f9c42c27f00b"}}
{"_id":{"$oid":"68c3ebdfa3afe7c4de9db7be"},"ticker":"COST","company":"Costco","averageCost":0,"__v":0,"position":false,"watchList":true,"userId":{"$oid":"68ac38cb3c01f9c42c27f00b"}}
{"_id":{"$oid":"68c3ec0aa3afe7c4de9db7c1"},"ticker":"COIN","company":"Coinbase","averageCost":0,"__v":0,"position":false,"watchList":true,"positionSize":15.29,"userId":{"$oid":"68ac38cb3c01f9c42c27f00b"}}
{"_id":{"$oid":"68c3ec20a3afe7c4de9db7c4"},"ticker":"CMS","company":"Consumer's Energy","averageCost":71.77,"__v":0,"position":true,"watchList":false,"positionSize":27,"userId":{"$oid":"68ac38cb3c01f9c42c27f00b"}}
{"_id":{"$oid":"68c3ec9ba3afe7c4de9db7cf"},"ticker":"CART","company":"Instacart (Maplebear Inc.)","averageCost":0,"__v":0,"position":false,"watchList":true,"userId":{"$oid":"68ac38cb3c01f9c42c27f00b"}}
{"_id":{"$oid":"68c3ecc1a3afe7c4de9db7d2"},"ticker":"BYRN","company":"Byrna Technologies","averageCost":0,"__v":0,"position":false,"watchList":true,"positionSize":12.78,"userId":{"$oid":"68ac38cb3c01f9c42c27f00b"}}
{"_id":{"$oid":"68c3ecf3a3afe7c4de9db7d5"},"ticker":"AMC","company":"AMC Entertainment","averageCost":0,"__v":0,"position":false,"watchList":true,"positionSize":14.82,"userId":{"$oid":"68ac38cb3c01f9c42c27f00b"}}
{"_id":{"$oid":"68c3f514a3afe7c4de9db7da"},"ticker":"PSKY","company":"Paramount Skydance Corporation Class B","averageCost":17.85,"__v":0,"position":true,"watchList":false,"positionSize":5.27,"userId":{"$oid":"68ac38cb3c01f9c42c27f00b"}}
{"_id":{"$oid":"68c4383da3afe7c4de9db7eb"},"ticker":"DKS","company":"Dicks Sporting Goods","averageCost":228.63,"__v":0,"position":true,"watchList":false,"positionSize":27,"userId":{"$oid":"68ac38cb3c01f9c42c27f00b"}}
{"_id":{"$oid":"68c44ae0a3afe7c4de9db892"},"ticker":"VZ","company":"Verizon","averageCost":0,"__v":0,"position":false,"watchList":true,"userId":{"$oid":"68ac38cb3c01f9c42c27f00b"}}
{"_id":{"$oid":"68c46092a3afe7c4de9db8f4"},"ticker":"CGNX","company":"Cognex","averageCost":45.57,"__v":0,"position":true,"watchList":false,"positionSize":34,"userId":{"$oid":"68ac38cb3c01f9c42c27f00b"}}
{"_id":{"$oid":"68c46c0da3afe7c4de9db932"},"ticker":"ZIM","company":"ZIM Integrated Shipping Services","averageCost":0,"__v":0,"position":false,"watchList":true,"positionSize":26,"userId":{"$oid":"68ac38cb3c01f9c42c27f00b"}}
{"_id":{"$oid":"68c46c1ca3afe7c4de9db935"},"ticker":"MSFT","company":"Microsoft","averageCost":0,"__v":0,"position":false,"watchList":true,"positionSize":39.44,"userId":{"$oid":"68ac38cb3c01f9c42c27f00b"}}
{"_id":{"$oid":"68c5b19a9cf4e3e56b331982"},"ticker":"AMZN","company":"Amazon","averageCost":0,"watchList":true,"position":false,"__v":0,"userId":{"$oid":"68ac38cb3c01f9c42c27f00b"}}
{"_id":{"$oid":"68c5cb365439473420d6ca5d"},"ticker":"AXP","company":"American Express","averageCost":336.43,"watchList":false,"position":true,"__v":0,"positionSize":22.32,"userId":{"$oid":"68ac38cb3c01f9c42c27f00b"}}
{"_id":{"$oid":"68c5cb375439473420d6ca60"},"ticker":"BA","company":"Boeing","averageCost":222.44,"watchList":false,"position":true,"__v":0,"positionSize":12,"userId":{"$oid":"68ac38cb3c01f9c42c27f00b"}}
{"_id":{"$oid":"68c5cb395439473420d6ca63"},"ticker":"BP","company":"British Petroleum","averageCost":35.03,"watchList":false,"position":true,"__v":0,"positionSize":26.01,"userId":{"$oid":"68ac38cb3c01f9c42c27f00b"}}
{"_id":{"$oid":"68c5cb3e5439473420d6ca66"},"ticker":"CDNS","company":"Cadence Design Systems","averageCost":0,"watchList":true,"position":false,"__v":0,"positionSize":10.22,"userId":{"$oid":"68ac38cb3c01f9c42c27f00b"}}
{"_id":{"$oid":"68c5cb425439473420d6ca69"},"ticker":"CELH","company":"Celsius","averageCost":54.48,"watchList":false,"position":true,"__v":0,"positionSize":27,"userId":{"$oid":"68ac38cb3c01f9c42c27f00b"}}
{"_id":{"$oid":"68c5cb435439473420d6ca6c"},"ticker":"CVNA","company":"Carvana","averageCost":0,"watchList":true,"position":false,"__v":0,"positionSize":9.16,"userId":{"$oid":"68ac38cb3c01f9c42c27f00b"}}
{"_id":{"$oid":"68c5cb485439473420d6ca6f"},"ticker":"DKNG","company":"","averageCost":null,"watchList":true,"position":false,"__v":0,"userId":{"$oid":"68ac38cb3c01f9c42c27f00b"}}
{"_id":{"$oid":"68c5cb4a5439473420d6ca72"},"ticker":"HAS","company":"Hasbro","averageCost":75.28,"watchList":false,"position":true,"__v":0,"positionSize":38,"userId":{"$oid":"68ac38cb3c01f9c42c27f00b"}}
{"_id":{"$oid":"68c5cb4e5439473420d6ca75"},"ticker":"HSY","company":"Hershey","averageCost":0,"watchList":true,"position":false,"__v":0,"positionSize":40.5,"userId":{"$oid":"68ac38cb3c01f9c42c27f00b"}}
{"_id":{"$oid":"68c5cb5c5439473420d6ca78"},"ticker":"INTC","company":"Intel","averageCost":29.99,"watchList":false,"position":true,"__v":0,"positionSize":4.83,"userId":{"$oid":"68ac38cb3c01f9c42c27f00b"}}
{"_id":{"$oid":"68c5cb5f5439473420d6ca7b"},"ticker":"LEVI","company":"Levi Strauss","averageCost":0,"watchList":true,"position":false,"__v":0,"positionSize":14.62,"userId":{"$oid":"68ac38cb3c01f9c42c27f00b"}}
{"_id":{"$oid":"68c5cb605439473420d6ca7e"},"ticker":"MA","company":"Mastercard","averageCost":0,"watchList":true,"position":false,"__v":0,"userId":{"$oid":"68ac38cb3c01f9c42c27f00b"}}
{"_id":{"$oid":"68c5cb625439473420d6ca81"},"ticker":"MP","company":"MP Materials","averageCost":0,"watchList":true,"position":false,"__v":0,"positionSize":5.55,"userId":{"$oid":"68ac38cb3c01f9c42c27f00b"}}
{"_id":{"$oid":"68c5cb645439473420d6ca84"},"ticker":"ROKU","company":"Roku","averageCost":0,"watchList":true,"position":false,"__v":0,"positionSize":15.12,"userId":{"$oid":"68ac38cb3c01f9c42c27f00b"}}
{"_id":{"$oid":"68c5cb665439473420d6ca87"},"ticker":"SCS","company":"Steelcase","averageCost":16.99,"watchList":false,"position":true,"__v":0,"positionSize":37,"userId":{"$oid":"68ac38cb3c01f9c42c27f00b"}}
{"_id":{"$oid":"68c5cb6c5439473420d6ca8a"},"ticker":"SHEL","company":"Shell","averageCost":72.91,"watchList":false,"position":true,"__v":0,"positionSize":37,"userId":{"$oid":"68ac38cb3c01f9c42c27f00b"}}
{"_id":{"$oid":"68c5cb6f5439473420d6ca8d"},"ticker":"SHOP","company":"Shopify","averageCost":0,"watchList":true,"position":false,"__v":0,"positionSize":6.32,"userId":{"$oid":"68ac38cb3c01f9c42c27f00b"}}
{"_id":{"$oid":"68c5cb755439473420d6ca90"},"ticker":"SNOW","company":"Snowflake","averageCost":0,"watchList":true,"position":false,"__v":0,"positionSize":16.96,"userId":{"$oid":"68ac38cb3c01f9c42c27f00b"}}
{"_id":{"$oid":"68c5cb775439473420d6ca93"},"ticker":"TJX","company":"TJX","averageCost":142.69,"watchList":false,"position":true,"__v":0,"positionSize":23,"userId":{"$oid":"68ac38cb3c01f9c42c27f00b"}}
{"_id":{"$oid":"68c5cb7d5439473420d6ca96"},"ticker":"WYNN","company":"Wynn Resorts","averageCost":128.31,"watchList":false,"position":true,"__v":0,"positionSize":20,"userId":{"$oid":"68ac38cb3c01f9c42c27f00b"}}
{"_id":{"$oid":"68c5cba35439473420d6ca9b"},"ticker":"DAL","company":"","averageCost":null,"watchList":true,"position":false,"__v":0,"userId":{"$oid":"68ac38cb3c01f9c42c27f00b"}}
{"_id":{"$oid":"68c5cba45439473420d6ca9e"},"ticker":"H","company":"Hyatt","averageCost":142.59,"watchList":false,"position":true,"__v":0,"positionSize":38,"userId":{"$oid":"68ac38cb3c01f9c42c27f00b"}}
{"_id":{"$oid":"68c5cba65439473420d6caa1"},"ticker":"MCD","company":"","averageCost":0,"watchList":true,"position":false,"__v":0,"userId":{"$oid":"68ac38cb3c01f9c42c27f00b"}}
{"_id":{"$oid":"68c5cba95439473420d6caa4"},"ticker":"ODP","company":"Office Depot","averageCost":27.8,"watchList":false,"position":true,"__v":0,"positionSize":1.99,"userId":{"$oid":"68ac38cb3c01f9c42c27f00b"}}
{"_id":{"$oid":"68c5cbaa5439473420d6caa7"},"ticker":"PEP","company":"","averageCost":null,"watchList":true,"position":false,"__v":0,"userId":{"$oid":"68ac38cb3c01f9c42c27f00b"}}
{"_id":{"$oid":"68c5cbac5439473420d6caaa"},"ticker":"PNC","company":"PNC Financial","averageCost":0,"watchList":true,"position":false,"__v":0,"positionSize":39.9,"userId":{"$oid":"68ac38cb3c01f9c42c27f00b"}}
{"_id":{"$oid":"68c5cbb25439473420d6cab0"},"ticker":"VAC","company":"","averageCost":null,"watchList":true,"position":false,"__v":0,"userId":{"$oid":"68ac38cb3c01f9c42c27f00b"}}
{"_id":{"$oid":"68c5cbcb5439473420d6cab5"},"ticker":"AAPL","company":"Apple","averageCost":239.15,"watchList":false,"position":true,"__v":0,"positionSize":6.12,"userId":{"$oid":"68ac38cb3c01f9c42c27f00b"}}
{"_id":{"$oid":"68c5cbce5439473420d6cab8"},"ticker":"BKNG","company":"Booking Holdings","averageCost":5554.65,"watchList":false,"position":true,"__v":0,"positionSize":34,"userId":{"$oid":"68ac38cb3c01f9c42c27f00b"}}
{"_id":{"$oid":"68c5cbd05439473420d6cabb"},"ticker":"BULL","company":"Webull","averageCost":14.1,"watchList":false,"position":true,"__v":0,"positionSize":5.15,"userId":{"$oid":"68ac38cb3c01f9c42c27f00b"}}
{"_id":{"$oid":"68c5cbd85439473420d6cabe"},"ticker":"BBY","company":"Best Buy","averageCost":75.3,"watchList":false,"position":true,"__v":0,"positionSize":15,"userId":{"$oid":"68ac38cb3c01f9c42c27f00b"}}
{"_id":{"$oid":"68c5cbdf5439473420d6cac1"},"ticker":"BRK-B","company":"","averageCost":496.83,"watchList":false,"position":true,"__v":0,"positionSize":40,"userId":{"$oid":"68ac38cb3c01f9c42c27f00b"}}
{"_id":{"$oid":"68c5cbe15439473420d6cac4"},"ticker":"LAD","company":"","averageCost":0,"watchList":true,"position":false,"__v":0,"userId":{"$oid":"68ac38cb3c01f9c42c27f00b"}}
{"_id":{"$oid":"68c5cbea5439473420d6cac7"},"ticker":"AAL","company":"American Airlines","averageCost":null,"watchList":true,"position":false,"__v":0,"userId":{"$oid":"68ac38cb3c01f9c42c27f00b"}}
{"_id":{"$oid":"68c5cbed5439473420d6caca"},"ticker":"JBLU","company":"","averageCost":0,"watchList":true,"position":false,"__v":0,"userId":{"$oid":"68ac38cb3c01f9c42c27f00b"}}
{"_id":{"$oid":"68c5cbef5439473420d6cacd"},"ticker":"NWL","company":"","averageCost":null,"watchList":true,"position":false,"__v":0,"userId":{"$oid":"68ac38cb3c01f9c42c27f00b"}}
{"_id":{"$oid":"68c5cbf25439473420d6cad0"},"ticker":"PG","company":"","averageCost":0,"watchList":true,"position":false,"__v":0,"userId":{"$oid":"68ac38cb3c01f9c42c27f00b"}}
{"_id":{"$oid":"68c5cbf55439473420d6cad3"},"ticker":"TSN","company":"","averageCost":0,"watchList":true,"position":false,"__v":0,"userId":{"$oid":"68ac38cb3c01f9c42c27f00b"}}
{"_id":{"$oid":"68c5cc5c5439473420d6cadd"},"ticker":"HBI","company":"Hanesbrands","averageCost":6.43,"watchList":false,"position":true,"__v":0,"positionSize":23.09,"userId":{"$oid":"68ac38cb3c01f9c42c27f00b"}}
{"_id":{"$oid":"68c5cc735439473420d6cae2"},"ticker":"CBRL","company":"Cracker Barrel","averageCost":0,"watchList":true,"position":false,"__v":0,"userId":{"$oid":"68ac38cb3c01f9c42c27f00b"}}
{"_id":{"$oid":"68c5cc765439473420d6cae5"},"ticker":"CSCO","company":"Cisco Systems","averageCost":0,"watchList":true,"position":false,"__v":0,"positionSize":40,"userId":{"$oid":"68ac38cb3c01f9c42c27f00b"}}
{"_id":{"$oid":"68c5cc785439473420d6cae8"},"ticker":"DIS","company":"","averageCost":null,"watchList":true,"position":false,"__v":0,"userId":{"$oid":"68ac38cb3c01f9c42c27f00b"}}
{"_id":{"$oid":"68c5cc7c5439473420d6caeb"},"ticker":"DPZ","company":"Domino's Pizza","averageCost":440.37,"watchList":false,"position":true,"__v":0,"positionSize":19,"userId":{"$oid":"68ac38cb3c01f9c42c27f00b"}}
{"_id":{"$oid":"68c5cc7e5439473420d6caee"},"ticker":"EAT","company":"","averageCost":null,"watchList":true,"position":false,"__v":0,"userId":{"$oid":"68ac38cb3c01f9c42c27f00b"}}
{"_id":{"$oid":"68c5cc815439473420d6caf1"},"ticker":"FLUT","company":"","averageCost":null,"watchList":true,"position":false,"__v":0,"userId":{"$oid":"68ac38cb3c01f9c42c27f00b"}}
{"_id":{"$oid":"68c5cc845439473420d6caf4"},"ticker":"INTU","company":"Intuit","averageCost":680.29,"watchList":false,"position":true,"__v":0,"positionSize":8.3,"userId":{"$oid":"68ac38cb3c01f9c42c27f00b"}}
{"_id":{"$oid":"68c5cc855439473420d6caf7"},"ticker":"KO","company":"","averageCost":null,"watchList":true,"position":false,"__v":0,"userId":{"$oid":"68ac38cb3c01f9c42c27f00b"}}
{"_id":{"$oid":"68c5cc885439473420d6cafa"},"ticker":"MGM","company":"MGM Resorts","averageCost":35.57,"watchList":false,"position":true,"__v":0,"positionSize":35,"userId":{"$oid":"68ac38cb3c01f9c42c27f00b"}}
{"_id":{"$oid":"68c5cc8d5439473420d6cafd"},"ticker":"NFLX","company":"","averageCost":null,"watchList":true,"position":false,"__v":0,"userId":{"$oid":"68ac38cb3c01f9c42c27f00b"}}
{"_id":{"$oid":"68c5cc955439473420d6cb00"},"ticker":"NKE","company":"","averageCost":null,"watchList":true,"position":false,"__v":0,"userId":{"$oid":"68ac38cb3c01f9c42c27f00b"}}
{"_id":{"$oid":"68c5cc975439473420d6cb03"},"ticker":"PINS","company":"","averageCost":null,"watchList":true,"position":false,"__v":0,"userId":{"$oid":"68ac38cb3c01f9c42c27f00b"}}
{"_id":{"$oid":"68c5cc995439473420d6cb06"},"ticker":"PLNT","company":"Planet Fitness","averageCost":103.61,"watchList":false,"position":true,"__v":0,"positionSize":17,"userId":{"$oid":"68ac38cb3c01f9c42c27f00b"}}
{"_id":{"$oid":"68c5cc9c5439473420d6cb09"},"ticker":"SCHW","company":"Charles Schwab","averageCost":95.77,"watchList":false,"position":true,"__v":0,"positionSize":15,"userId":{"$oid":"68ac38cb3c01f9c42c27f00b"}}
{"_id":{"$oid":"68c5cc9e5439473420d6cb0c"},"ticker":"SPOT","company":"Spotify","averageCost":0,"watchList":true,"position":false,"__v":0,"positionSize":10.05,"userId":{"$oid":"68ac38cb3c01f9c42c27f00b"}}
{"_id":{"$oid":"68c5cca45439473420d6cb12"},"ticker":"TMUS","company":"","averageCost":0,"watchList":true,"position":false,"__v":0,"userId":{"$oid":"68ac38cb3c01f9c42c27f00b"}}
{"_id":{"$oid":"68c5cca65439473420d6cb15"},"ticker":"V","company":"","averageCost":0,"watchList":true,"position":false,"__v":0,"userId":{"$oid":"68ac38cb3c01f9c42c27f00b"}}
{"_id":{"$oid":"68c5cca85439473420d6cb18"},"ticker":"XYZ","company":"Block","averageCost":0,"watchList":true,"position":false,"__v":0,"positionSize":26.37,"userId":{"$oid":"68ac38cb3c01f9c42c27f00b"}}
{"_id":{"$oid":"68c5ccb65439473420d6cb1b"},"ticker":"ADBE","company":"Adobe","averageCost":0,"watchList":true,"position":false,"__v":0,"positionSize":14.31,"userId":{"$oid":"68ac38cb3c01f9c42c27f00b"}}
{"_id":{"$oid":"68c5ccb85439473420d6cb1e"},"ticker":"ANF","company":"","averageCost":null,"watchList":true,"position":false,"__v":0,"userId":{"$oid":"68ac38cb3c01f9c42c27f00b"}}
{"_id":{"$oid":"68c5ccbb5439473420d6cb21"},"ticker":"BBWI","company":"Bath & Body Works","averageCost":26.39,"watchList":false,"position":true,"__v":0,"positionSize":36,"userId":{"$oid":"68ac38cb3c01f9c42c27f00b"}}
{"_id":{"$oid":"68c5ccbf5439473420d6cb24"},"ticker":"BLSH","company":"Bullish","averageCost":0,"watchList":true,"position":false,"__v":0,"positionSize":5.77,"userId":{"$oid":"68ac38cb3c01f9c42c27f00b"}}
{"_id":{"$oid":"68c5ccc15439473420d6cb27"},"ticker":"BUD","company":"","averageCost":59.01,"watchList":false,"position":true,"__v":0,"positionSize":30,"userId":{"$oid":"68ac38cb3c01f9c42c27f00b"}}
{"_id":{"$oid":"68c5ccc35439473420d6cb2a"},"ticker":"CAVA","company":"CAVA","averageCost":0,"watchList":true,"position":false,"__v":0,"positionSize":12,"userId":{"$oid":"68ac38cb3c01f9c42c27f00b"}}
{"_id":{"$oid":"68c5cccc5439473420d6cb2d"},"ticker":"CETX","company":"","averageCost":null,"watchList":true,"position":false,"__v":0,"userId":{"$oid":"68ac38cb3c01f9c42c27f00b"}}
{"_id":{"$oid":"68c5cccf5439473420d6cb30"},"ticker":"CHD","company":"","averageCost":null,"watchList":true,"position":false,"__v":0,"userId":{"$oid":"68ac38cb3c01f9c42c27f00b"}}
{"_id":{"$oid":"68c5ccd15439473420d6cb33"},"ticker":"CHWY","company":"Chewy","averageCost":39.5,"watchList":false,"position":true,"__v":0,"positionSize":10,"userId":{"$oid":"68ac38cb3c01f9c42c27f00b"}}
{"_id":{"$oid":"68c5ccd35439473420d6cb36"},"ticker":"CMG","company":"Chipotle","averageCost":39.96,"watchList":false,"position":true,"__v":0,"positionSize":34,"userId":{"$oid":"68ac38cb3c01f9c42c27f00b"}}
{"_id":{"$oid":"68c5ccdd5439473420d6cb39"},"ticker":"CRM","company":"Salesforce","averageCost":0,"watchList":true,"position":false,"__v":0,"positionSize":39.7,"userId":{"$oid":"68ac38cb3c01f9c42c27f00b"}}
{"_id":{"$oid":"68c5cce05439473420d6cb3c"},"ticker":"CZR","company":"Caesars Entertainment","averageCost":25.98,"watchList":false,"position":true,"__v":0,"positionSize":35,"userId":{"$oid":"68ac38cb3c01f9c42c27f00b"}}
{"_id":{"$oid":"68c5cce15439473420d6cb3f"},"ticker":"DNUT","company":"Krispy Kreme","averageCost":3.45,"watchList":false,"position":true,"__v":0,"positionSize":11,"userId":{"$oid":"68ac38cb3c01f9c42c27f00b"}}
{"_id":{"$oid":"68c5cce65439473420d6cb45"},"ticker":"FIG","company":"Figma","averageCost":0,"watchList":true,"position":false,"__v":0,"positionSize":14.67,"userId":{"$oid":"68ac38cb3c01f9c42c27f00b"}}
{"_id":{"$oid":"68c5cce75439473420d6cb48"},"ticker":"HON","company":"","averageCost":null,"watchList":true,"position":false,"__v":0,"userId":{"$oid":"68ac38cb3c01f9c42c27f00b"}}
{"_id":{"$oid":"68c5cceb5439473420d6cb4b"},"ticker":"KDP","company":"","averageCost":null,"watchList":true,"position":false,"__v":0,"userId":{"$oid":"68ac38cb3c01f9c42c27f00b"}}
{"_id":{"$oid":"68c5cced5439473420d6cb4e"},"ticker":"KHC","company":"Kraft Foods","averageCost":0,"watchList":true,"position":false,"__v":0,"positionSize":27.18,"userId":{"$oid":"68ac38cb3c01f9c42c27f00b"}}
{"_id":{"$oid":"68c5ccf15439473420d6cb51"},"ticker":"KMX","company":"","averageCost":null,"watchList":true,"position":false,"__v":0,"userId":{"$oid":"68ac38cb3c01f9c42c27f00b"}}
{"_id":{"$oid":"68c5ccf35439473420d6cb54"},"ticker":"LULU","company":"Lululemon","averageCost":169.46,"watchList":false,"position":true,"__v":0,"positionSize":18.32,"userId":{"$oid":"68ac38cb3c01f9c42c27f00b"}}
{"_id":{"$oid":"68c5ccfc5439473420d6cb57"},"ticker":"NVO","company":"Novo Nordisk","averageCost":0,"watchList":true,"position":false,"__v":0,"positionSize":9.6,"userId":{"$oid":"68ac38cb3c01f9c42c27f00b"}}
{"_id":{"$oid":"68c5ccff5439473420d6cb5a"},"ticker":"PFE","company":"","averageCost":null,"watchList":true,"position":false,"__v":0,"userId":{"$oid":"68ac38cb3c01f9c42c27f00b"}}
{"_id":{"$oid":"68c5cd015439473420d6cb5d"},"ticker":"PLAY","company":"Dave & Buster's","averageCost":0,"watchList":true,"position":false,"__v":0,"userId":{"$oid":"68ac38cb3c01f9c42c27f00b"}}
{"_id":{"$oid":"68c5cd035439473420d6cb60"},"ticker":"PYPL","company":"PayPal","averageCost":0,"watchList":true,"position":false,"__v":0,"userId":{"$oid":"68ac38cb3c01f9c42c27f00b"}}
{"_id":{"$oid":"68c5cd055439473420d6cb63"},"ticker":"SBUX","company":"Starbucks","averageCost":0,"watchList":true,"position":false,"__v":0,"positionSize":24.1,"userId":{"$oid":"68ac38cb3c01f9c42c27f00b"}}
{"_id":{"$oid":"68c5cd085439473420d6cb66"},"ticker":"STZ","company":"","averageCost":null,"watchList":true,"position":false,"__v":0,"userId":{"$oid":"68ac38cb3c01f9c42c27f00b"}}
{"_id":{"$oid":"68c5cd0c5439473420d6cb69"},"ticker":"TAP","company":"","averageCost":null,"watchList":true,"position":false,"__v":0,"userId":{"$oid":"68ac38cb3c01f9c42c27f00b"}}
{"_id":{"$oid":"68c5cd0e5439473420d6cb6c"},"ticker":"TGT","company":"","averageCost":null,"watchList":true,"position":false,"__v":0,"userId":{"$oid":"68ac38cb3c01f9c42c27f00b"}}
{"_id":{"$oid":"68c5cd105439473420d6cb6f"},"ticker":"TTD","company":"Trade Desk","averageCost":47.24,"watchList":false,"position":true,"__v":0,"positionSize":13.88,"userId":{"$oid":"68ac38cb3c01f9c42c27f00b"}}
{"_id":{"$oid":"68c5cd125439473420d6cb72"},"ticker":"TWLO","company":"","averageCost":0,"watchList":true,"position":false,"__v":0,"userId":{"$oid":"68ac38cb3c01f9c42c27f00b"}}
{"_id":{"$oid":"68c5cd195439473420d6cb75"},"ticker":"TXN","company":"","averageCost":0,"watchList":true,"position":false,"__v":0,"userId":{"$oid":"68ac38cb3c01f9c42c27f00b"}}
{"_id":{"$oid":"68c5cd1b5439473420d6cb78"},"ticker":"UPS","company":"UPS","averageCost":0,"watchList":true,"position":false,"__v":0,"userId":{"$oid":"68ac38cb3c01f9c42c27f00b"}}
{"_id":{"$oid":"68c5cd1f5439473420d6cb7b"},"ticker":"WDFC","company":"","averageCost":0,"watchList":true,"position":false,"__v":0,"userId":{"$oid":"68ac38cb3c01f9c42c27f00b"}}
{"_id":{"$oid":"68c5cd205439473420d6cb7e"},"ticker":"WEN","company":"","averageCost":null,"watchList":true,"position":false,"__v":0,"userId":{"$oid":"68ac38cb3c01f9c42c27f00b"}}
{"_id":{"$oid":"68c5cd225439473420d6cb81"},"ticker":"WING","company":"","averageCost":null,"watchList":true,"position":false,"__v":0,"userId":{"$oid":"68ac38cb3c01f9c42c27f00b"}}
{"_id":{"$oid":"68c7aebd5439473420d6cba2"},"ticker":"NBIS","company":"Nebius Group","averageCost":95.12,"watchList":false,"position":true,"__v":0,"positionSize":3.38,"userId":{"$oid":"68ac38cb3c01f9c42c27f00b"}}
{"_id":{"$oid":"68c7bf2a5439473420d6cbad"},"ticker":"LPLA","company":"LPL Financial","averageCost":0,"watchList":true,"position":false,"__v":0,"userId":{"$oid":"68ac38cb3c01f9c42c27f00b"}}
{"_id":{"$oid":"68c7ccb05439473420d6cbb5"},"ticker":"SLV","company":"iShares Silver Trust","averageCost":39.86,"watchList":false,"position":true,"__v":0,"positionSize":19.94,"userId":{"$oid":"68ac38cb3c01f9c42c27f00b"}}
{"_id":{"$oid":"68c7cccc5439473420d6cbb8"},"ticker":"ICOP","company":"iShares Trust iShares Copper and Metals Mining ETF","averageCost":34.75,"watchList":false,"position":true,"__v":0,"positionSize":17.41,"userId":{"$oid":"68ac38cb3c01f9c42c27f00b"}}
{"_id":{"$oid":"68c827bc5439473420d6cc35"},"ticker":"BBAI","company":"BigBear.ai","averageCost":5.06,"watchList":false,"position":true,"__v":0,"positionSize":2.02,"userId":{"$oid":"68ac38cb3c01f9c42c27f00b"}}
{"_id":{"$oid":"68c82dc05439473420d6cc4a"},"ticker":"KR","company":"Kroger","averageCost":null,"watchList":true,"position":false,"__v":0,"userId":{"$oid":"68ac38cb3c01f9c42c27f00b"}}
{"_id":{"$oid":"68c8481f5439473420d6ccab"},"ticker":"AMD","company":"AMD","averageCost":0,"watchList":true,"position":false,"__v":0,"positionSize":14.82,"userId":{"$oid":"68ac38cb3c01f9c42c27f00b"}}
{"_id":{"$oid":"68c85a4b5439473420d6ccdd"},"ticker":"MU","company":"Micron Technology","averageCost":0,"watchList":true,"position":false,"__v":0,"positionSize":7.07,"userId":{"$oid":"68ac38cb3c01f9c42c27f00b"}}
{"_id":{"$oid":"68c952a65b54c7cdd64fec38"},"ticker":"RGTI","company":"Rigetti Computing","averageCost":19.22,"watchList":false,"position":true,"__v":0,"positionSize":1.51,"userId":{"$oid":"68ac38cb3c01f9c42c27f00b"}}
{"_id":{"$oid":"68c963fe5b54c7cdd64fec42"},"ticker":"MRK","company":"Merck","averageCost":null,"watchList":true,"position":false,"__v":0,"userId":{"$oid":"68ac38cb3c01f9c42c27f00b"}}
{"_id":{"$oid":"68cace137091c0f01c55279f"},"ticker":"YYAI","company":"Connexa Sports","averageCost":2.45,"watchList":false,"position":true,"__v":0,"positionSize":5,"userId":{"$oid":"68ac38cb3c01f9c42c27f00b"}}
{"_id":{"$oid":"68cadf887091c0f01c55281b"},"ticker":"STUB","company":"StubHub","averageCost":0,"watchList":true,"position":false,"__v":0,"userId":{"$oid":"68ac38cb3c01f9c42c27f00b"}}
{"_id":{"$oid":"68cbe0e67091c0f01c552938"},"ticker":"NXST","company":"Nexstar Media Group","averageCost":0,"watchList":true,"position":false,"__v":0,"userId":{"$oid":"68ac38cb3c01f9c42c27f00b"}}
{"_id":{"$oid":"68cbf11f7091c0f01c552977"},"ticker":"SBGI","company":"Sinclair, Inc. Class A","averageCost":14.28,"watchList":false,"position":true,"__v":0,"positionSize":26.91,"userId":{"$oid":"68ac38cb3c01f9c42c27f00b"}}
{"_id":{"$oid":"68cbfa737091c0f01c552983"},"ticker":"FANG","company":"Diamondback Energy","averageCost":142.72,"watchList":false,"position":true,"__v":0,"positionSize":14,"userId":{"$oid":"68ac38cb3c01f9c42c27f00b"}}
{"_id":{"$oid":"68cc00747091c0f01c5529a1"},"ticker":"RL","company":"Ralph Lauren","averageCost":0,"watchList":true,"position":false,"__v":0,"userId":{"$oid":"68ac38cb3c01f9c42c27f00b"}}
{"_id":{"$oid":"68cc5ee47091c0f01c552ac9"},"ticker":"SERV","company":"Serve Robotics Inc.","averageCost":0,"watchList":true,"position":false,"__v":0,"positionSize":4.54,"userId":{"$oid":"68ac38cb3c01f9c42c27f00b"}}
{"_id":{"$oid":"68cd6e817091c0f01c552b26"},"ticker":"SE","company":"Sea Limited","averageCost":null,"watchList":true,"position":false,"__v":0,"userId":{"$oid":"68ac38cb3c01f9c42c27f00b"}}
{"_id":{"$oid":"68cd7f49c32ca039f4cafa4e"},"ticker":"MPC","company":"Marathon Petroleum","averageCost":183.75,"watchList":false,"position":true,"__v":0,"positionSize":11.08,"userId":{"$oid":"68ac38cb3c01f9c42c27f00b"}}
{"_id":{"$oid":"68ce0cdec32ca039f4cafaec"},"ticker":"BMNR","company":"BitMine Immersion Technologies","averageCost":0,"watchList":true,"position":false,"__v":0,"positionSize":9,"userId":{"$oid":"68ac38cb3c01f9c42c27f00b"}}
{"_id":{"$oid":"68ce0d80c32ca039f4cafaf2"},"ticker":"BABA","company":"Alibaba","averageCost":165.86,"watchList":false,"position":true,"__v":0,"positionSize":12.86,"userId":{"$oid":"68ac38cb3c01f9c42c27f00b"}}
{"_id":{"$oid":"68ce6cc2c32ca039f4cafafc"},"ticker":"JD","company":"JD.com","averageCost":0,"watchList":true,"position":false,"__v":0,"positionSize":35.12,"userId":{"$oid":"68ac38cb3c01f9c42c27f00b"}}
{"_id":{"$oid":"68ce6e73c32ca039f4cafb02"},"ticker":"BRKR","company":"Bruker","averageCost":0,"watchList":true,"position":false,"__v":0,"positionSize":10,"userId":{"$oid":"68ac38cb3c01f9c42c27f00b"}}
{"_id":{"$oid":"68ce6e95c32ca039f4cafb05"},"ticker":"REGN","company":"Regeneron","averageCost":0,"watchList":true,"position":false,"__v":0,"positionSize":10.64,"userId":{"$oid":"68ac38cb3c01f9c42c27f00b"}}
{"_id":{"$oid":"68ce72e2c32ca039f4cafb0d"},"ticker":"ETH-USD","company":"Ethereum","averageCost":null,"watchList":true,"position":false,"__v":0,"userId":{"$oid":"68ac38cb3c01f9c42c27f00b"}}
{"_id":{"$oid":"68ce73d8c32ca039f4cafb19"},"ticker":"DOGE-USD","company":"Dogecoin","averageCost":null,"watchList":true,"position":false,"__v":0,"userId":{"$oid":"68ac38cb3c01f9c42c27f00b"}}
{"_id":{"$oid":"68cfb9a0c32ca039f4cafb23"},"ticker":"SMR","company":"NuScale Power","averageCost":0,"watchList":true,"position":false,"__v":0,"positionSize":15.68,"userId":{"$oid":"68ac38cb3c01f9c42c27f00b"}}
{"_id":{"$oid":"68d145262d210a9270df43c5"},"ticker":"STX","company":"Seagate Technology","averageCost":0,"watchList":true,"position":false,"__v":0,"positionSize":10.94,"userId":{"$oid":"68ac38cb3c01f9c42c27f00b"}}
{"_id":{"$oid":"68d145592d210a9270df43c8"},"ticker":"WDC","company":"Western Digital","averageCost":109.49,"watchList":false,"position":true,"__v":0,"positionSize":6.18,"userId":{"$oid":"68ac38cb3c01f9c42c27f00b"}}
{"_id":{"$oid":"68d146022d210a9270df43cb"},"ticker":"NEM","company":"Newmont","averageCost":83.68,"watchList":false,"position":true,"__v":0,"positionSize":13.97,"userId":{"$oid":"68ac38cb3c01f9c42c27f00b"}}
{"_id":{"$oid":"68d146852d210a9270df43ce"},"ticker":"GEV","company":"GE Vernova","averageCost":null,"watchList":true,"position":false,"__v":0,"userId":{"$oid":"68ac38cb3c01f9c42c27f00b"}}
{"_id":{"$oid":"68d146dd2d210a9270df43d1"},"ticker":"NRG","company":"NRG Energy","averageCost":167.99,"watchList":false,"position":true,"__v":0,"positionSize":31,"userId":{"$oid":"68ac38cb3c01f9c42c27f00b"}}
{"_id":{"$oid":"68d147492d210a9270df43d4"},"ticker":"APH","company":"Amphenol","averageCost":122.76,"watchList":false,"position":true,"__v":0,"positionSize":40,"userId":{"$oid":"68ac38cb3c01f9c42c27f00b"}}
{"_id":{"$oid":"68d147fc2d210a9270df43d7"},"ticker":"TPR","company":"Tapestry","averageCost":0,"watchList":true,"position":false,"__v":0,"positionSize":19.94,"userId":{"$oid":"68ac38cb3c01f9c42c27f00b"}}
{"_id":{"$oid":"68d148392d210a9270df43da"},"ticker":"LRCX","company":"Lam Research Corp","averageCost":129.06,"watchList":false,"position":true,"__v":0,"positionSize":11.98,"userId":{"$oid":"68ac38cb3c01f9c42c27f00b"}}
{"_id":{"$oid":"68d148952d210a9270df43dd"},"ticker":"KLAC","company":"KLA","averageCost":1053.58,"watchList":false,"position":true,"__v":0,"positionSize":7.07,"userId":{"$oid":"68ac38cb3c01f9c42c27f00b"}}
{"_id":{"$oid":"68d148dc2d210a9270df43e0"},"ticker":"IDXX","company":"IDEXX Laboratories","averageCost":null,"watchList":true,"position":false,"__v":0,"userId":{"$oid":"68ac38cb3c01f9c42c27f00b"}}
{"_id":{"$oid":"68d14a5d2d210a9270df43e3"},"ticker":"NIO","company":"NIO","averageCost":0,"watchList":true,"position":false,"__v":0,"positionSize":11.96,"userId":{"$oid":"68ac38cb3c01f9c42c27f00b"}}
{"_id":{"$oid":"68d14a772d210a9270df43e6"},"ticker":"MBX","company":"MBX Biosciences","averageCost":23.06,"watchList":false,"position":true,"__v":0,"positionSize":0.8673,"userId":{"$oid":"68ac38cb3c01f9c42c27f00b"}}
{"_id":{"$oid":"68d15cc92d210a9270df4459"},"ticker":"NI","company":"NiSource","averageCost":41.49,"watchList":false,"position":true,"__v":0,"positionSize":16,"userId":{"$oid":"68ac38cb3c01f9c42c27f00b"}}
{"_id":{"$oid":"68d160202d210a9270df4484"},"ticker":"GLW","company":"Corning","averageCost":0,"watchList":true,"position":false,"__v":0,"positionSize":20,"userId":{"$oid":"68ac38cb3c01f9c42c27f00b"}}
{"_id":{"$oid":"68d1e4d02d210a9270df457e"},"ticker":"PGY","company":"Pagaya Technologies","averageCost":null,"watchList":true,"position":false,"__v":0,"userId":{"$oid":"68ac38cb3c01f9c42c27f00b"}}
{"_id":{"$oid":"68d1e5342d210a9270df4581"},"ticker":"QBTS","company":"D-Wave Quantum","averageCost":27,"watchList":false,"position":true,"__v":0,"positionSize":2,"userId":{"$oid":"68ac38cb3c01f9c42c27f00b"}}
{"_id":{"$oid":"68d1e57e2d210a9270df4584"},"ticker":"JMIA","company":"Jumia Technologies","averageCost":0,"watchList":true,"position":false,"__v":0,"userId":{"$oid":"68ac38cb3c01f9c42c27f00b"}}
{"_id":{"$oid":"68d1e60e2d210a9270df4588"},"ticker":"OUST","company":"Ouster","averageCost":null,"watchList":true,"position":false,"__v":0,"userId":{"$oid":"68ac38cb3c01f9c42c27f00b"}}
{"_id":{"$oid":"68d1e6b82d210a9270df458b"},"ticker":"PL","company":"Planet Labs","averageCost":11.62,"watchList":false,"position":true,"__v":0,"positionSize":4.09,"userId":{"$oid":"68ac38cb3c01f9c42c27f00b"}}
{"_id":{"$oid":"68d1e7532d210a9270df458e"},"ticker":"ONDS","company":"Ondas","averageCost":7.39,"watchList":false,"position":true,"__v":0,"positionSize":5.9,"userId":{"$oid":"68ac38cb3c01f9c42c27f00b"}}
{"_id":{"$oid":"68d1e8932d210a9270df4591"},"ticker":"QS","company":"QuantumScape","averageCost":12.99,"watchList":false,"position":true,"__v":0,"positionSize":4.86,"userId":{"$oid":"68ac38cb3c01f9c42c27f00b"}}
{"_id":{"$oid":"68d24fa42d210a9270df45a4"},"ticker":"HOND","company":"HCM II Acquisition Corp","averageCost":15.84,"watchList":false,"position":true,"__v":0,"positionSize":2,"userId":{"$oid":"68ac38cb3c01f9c42c27f00b"}}
{"_id":{"$oid":"68d28da0f3d73d8053a12e43"},"ticker":"IMSR","company":"Terrestrial Energy","averageCost":null,"watchList":true,"position":false,"__v":0,"userId":{"$oid":"68ac38cb3c01f9c42c27f00b"}}
{"_id":{"$oid":"68d40444f3d73d8053a13053"},"ticker":"HAL","company":"Halliburton","averageCost":25.15,"watchList":false,"position":true,"__v":0,"positionSize":5,"userId":{"$oid":"68ac38cb3c01f9c42c27f00b"}}
{"_id":{"$oid":"68d4045ef3d73d8053a13056"},"ticker":"LMT","company":"Lockheed","averageCost":0,"watchList":true,"position":false,"__v":0,"userId":{"$oid":"68ac38cb3c01f9c42c27f00b"}}
{"_id":{"$oid":"68d9ff7dc5ba14cbce603614"},"ticker":"DLR","company":"Digital Realty Trust","averageCost":null,"userId":{"$oid":"68ac38cb3c01f9c42c27f00b"},"watchList":true,"position":false,"__v":0}
{"_id":{"$oid":"68d9ff9ac5ba14cbce603617"},"ticker":"EQIX","company":"Equinix","averageCost":null,"userId":{"$oid":"68ac38cb3c01f9c42c27f00b"},"watchList":true,"position":false,"__v":0}
{"_id":{"$oid":"68d9ffd6c5ba14cbce60361a"},"ticker":"NEE","company":"NextEra Energy","averageCost":null,"userId":{"$oid":"68ac38cb3c01f9c42c27f00b"},"watchList":true,"position":false,"__v":0}
{"_id":{"$oid":"68da000cc5ba14cbce60361d"},"ticker":"CEG","company":"Constellation Energy","averageCost":null,"userId":{"$oid":"68ac38cb3c01f9c42c27f00b"},"watchList":true,"position":false,"__v":0}
{"_id":{"$oid":"68da003bc5ba14cbce603620"},"ticker":"ETN","company":"Eaton","averageCost":null,"userId":{"$oid":"68ac38cb3c01f9c42c27f00b"},"watchList":true,"position":false,"__v":0}
{"_id":{"$oid":"68da016bc5ba14cbce603623"},"ticker":"VRT","company":"Vertiv","averageCost":null,"userId":{"$oid":"68ac38cb3c01f9c42c27f00b"},"watchList":true,"position":false,"__v":0}
